{
  "_fv": 79,
  "_type": "recipe",
  "definition": {
    "recipeType": "Crafting",
    "recipeRetstackSize": 1,
    "group": "",
    "unlockingItems": [
      {
        "value": "Blocks.FURNACE"
      },
      {
        "value": "CUSTOM:ReinforcedStick"
      }
    ],
    "cookingBookCategory": "MISC",
    "xpReward": 0.0,
    "cookingTime": 200,
    "craftingBookCategory": "MISC",
    "recipeShapeless": false,
    "recipeSlots": [
      {
        "value": "Blocks.SMOKER"
      },
      {
        "value": "Blocks.FURNACE"
      },
      {
        "value": "Blocks.BLAST_FURNACE"
      },
      {
        "value": "Blocks.COAL_BLOCK"
      },
      {
        "value": "CUSTOM:ReinforcedStick"
      },
      {
        "value": "Blocks.COAL_BLOCK"
      },
      {
        "value": ""
      },
      {
        "value": "CUSTOM:ReinforcedStick"
      },
      {
        "value": ""
      }
    ],
    "recipeReturnStack": {
      "value": "CUSTOM:AmetyhstPickaxe"
    },
    "name": "furnace_crafting",
    "namespace": "mod"
  }
}