{
  "_fv": 79,
  "_type": "tool",
  "definition": {
    "toolType": "Sword",
    "renderType": 0,
    "blockingRenderType": 0,
    "texture": "voideater",
    "customModelName": "Normal",
    "blockingModelName": "Normal blocking",
    "guiTexture": "",
    "name": "Life Stealer",
    "specialInformation": {
      "fixedValue": []
    },
    "creativeTabs": [
      {
        "value": "COMBAT"
      }
    ],
    "efficiency": 4.0,
    "attackSpeed": 0.8,
    "enchantability": 2,
    "damageVsEntity": 10.0,
    "usageCount": 9200,
    "glowCondition": {
      "fixedValue": false
    },
    "repairItems": [
      {
        "value": "Items.TOTEM_OF_UNDYING"
      }
    ],
    "immuneToFire": false,
    "blockDropsTier": "WOOD",
    "blocksAffected": [],
    "stayInGridWhenCrafting": false,
    "damageOnCrafting": false,
    "onEntityHitWith": {
      "name": "LifeStealerLivingEntityIsHitWithTool"
    }
  }
}